ehr/datasets/__init__.py
ehr/datasets/mimic/__init__.py
ehr/datasets/mimic/constants.py
ehr/datasets/ohdsi/__init__.py
ehr/datasets/ohdsi/constants.py
ehr/utilities/__init__.py
ehr/utilities/fs.py
ehr-0.0.dev1.dist-info/LICENSE
ehr-0.0.dev1.dist-info/METADATA
ehr-0.0.dev1.dist-info/WHEEL
ehr-0.0.dev1.dist-info/top_level.txt
ehr-0.0.dev1.dist-info/RECORD
